signalr/__init__.py
signalr/_connection.py
signalr/events/__init__.py
signalr/events/_events.py
signalr/hubs/__init__.py
signalr/hubs/_hub.py
signalr/transports/__init__.py
signalr/transports/_auto_transport.py
signalr/transports/_sse_transport.py
signalr/transports/_transport.py
signalr/transports/_ws_transport.py
signalr_client_threads-0.0.12.dist-info/DESCRIPTION.rst
signalr_client_threads-0.0.12.dist-info/METADATA
signalr_client_threads-0.0.12.dist-info/RECORD
signalr_client_threads-0.0.12.dist-info/WHEEL
signalr_client_threads-0.0.12.dist-info/metadata.json
signalr_client_threads-0.0.12.dist-info/top_level.txt
