Metadata-Version: 1.1
Name: signalr-client-threads
Version: 0.0.12
Summary: Fork of SignalR client for Python based on threads instead of gevent
Home-page: https://github.com/PawelTroka/signalr-client-threads
Author: Taucraft Limited, Michael Herrmann, Pawel Troka
Author-email: info@taucraft.com, pawel.troka@outlook.com
License: Apache
Keywords: signalr
Platform: UNKNOWN
Classifier: Development Status :: 3 - Alpha
Classifier: Intended Audience :: Developers
Classifier: Topic :: Software Development :: Libraries :: Python Modules
Classifier: License :: OSI Approved :: Apache Software License
Classifier: Programming Language :: Python :: 2.7
Classifier: Programming Language :: Python :: 3
Classifier: Programming Language :: Python :: 3.2
Classifier: Programming Language :: Python :: 3.3
Classifier: Programming Language :: Python :: 3.4
Classifier: Programming Language :: Python :: 3.5
Classifier: Programming Language :: Python :: 3.6
Classifier: Programming Language :: Python :: 3.7
